{"header":{"avatar":"6 School St., Montgomery","name":"Sudipt Dabral","job":"Web Developer","bio":"","email":"sudiptwork1999@gmail.com","icon":{"github":"www.github.com/sudipt1999","linkdin":"https://www.linkedin.com/in/sudipt-dabral-15b516165/","facebook":"https://www.facebook.com/in/sudiptdabral","twitter":"twitter","website":"website"}},"language":[{"lang":"","perc":""}],"projects":[{"name":"","link":"","desc":""}],"experience":[{"name":"","job":"","date":{"start":"","end":""}}],"eduandcert":{"edu":[{"title":"","name":"","date":{"start":"","end":""}}]}}